icsbom/__init__.py
icsbom/__main__.py
icsbom/icsbom.py
icsbom-1.2.0.dist-info/COPYING.txt
icsbom-1.2.0.dist-info/LICENSES/CC-BY-SA-4.0.txt
icsbom-1.2.0.dist-info/LICENSES/GPL-3.0-or-later.txt
icsbom-1.2.0.dist-info/LICENSES/MIT.txt
icsbom-1.2.0.dist-info/METADATA
icsbom-1.2.0.dist-info/WHEEL
icsbom-1.2.0.dist-info/entry_points.txt
icsbom-1.2.0.dist-info/RECORD
