Metadata-Version: 2.3
Name: icsbom
Version: 1.2.0
Summary: icsbom is a tool developed by Integrated Computer Solutions (ICS) for converting Software Bill of Materials (SBoM) into a Vex File.
Author: Michael Dingwall
Author-email: mdingwall@ics.com
Requires-Python: >=3.9,<4.0
Classifier: Programming Language :: Python :: 3
Classifier: Programming Language :: Python :: 3.9
Classifier: Programming Language :: Python :: 3.10
Classifier: Programming Language :: Python :: 3.11
Classifier: Programming Language :: Python :: 3.12
Classifier: Programming Language :: Python :: 3.13
Requires-Dist: ics_sbom_libs (>=1.2.1)
Requires-Dist: rich
Requires-Dist: rich-argparse
